{"2025-12-01": [{"timeframe": "10:00 - 12:00", "start": "10:00", "end": "12:00", "title": "Electrical Physics", "course_code": "TE00DH11-3002", "location": "ICT_C2036, Elektroniikkalaboratorio, ICT-City"}, {"timeframe": "12:00 - 14:00", "start": "12:00", "end": "14:00", "title": "Introduction to Programming", "course_code": "TE00CS88-3006", "location": "LEM_A176, IT-tila Micrococcus - koneilla, Lemppari"}], "2025-12-02": [{"timeframe": "8:00 - 10:00", "start": "8:00", "end": "10:00", "title": "Introduction to Programming", "course_code": "TE00CS88-3006", "location": "LEM_A177, IT-tila Saccharomyces - koneilla, Lemppari"}, {"timeframe": "10:00 - 12:00", "start": "10:00", "end": "12:00", "title": "Electrical Physics", "course_code": "TE00DH11-3002", "location": "ICT_C2036, Elektroniikkalaboratorio, ICT-City"}], "2025-12-03": [{"timeframe": "8:00 - 12:00", "start": "8:00", "end": "12:00", "title": "SUSTIS Kest\u00e4v\u00e4n kehityksen projekti", "course_code": "TE00CQ24-3001", "location": "EDU_2025_2026, Oppimistila avo byod, EduCity\nEDU_2033, Oppimistila avo muunto byod, EduCity\nEDU_3026_3027, Oppimistila avo byod, EduCity\nEDU_3076, Oppimistila avo byod, EduCity\nEDU_3074, Oppimistila avo byod, EduCity\nEDU_3033, Oppimistila avo byod, EduCity\nEDU_3028, Oppimistila avo muunto byod, EduCity\nEDU_2031, Oppimistila avo, EduCity\nEDU_2029, Oppimistila avo, EduCity\nEDU_2042, Oppimistila avo muunto byod, EduCity\nEDU_3036, Oppimistila avo muunto byod, EduCity\nEDU_3073, Oppimistila avo muunto byod, EduCity\nEDU_3015, Katri (10 hl\u00f6), EduCity\nEDU_3075, Marjukka (16 hl\u00f6), EduCity\nEDU_2048, Lyyli (10 hl\u00f6), EduCity\nEDU_2028, Ryhm\u00e4ty\u00f6 (10 hl\u00f6), EduCity\nEDU_2065.2, Ryhm\u00e4ty\u00f6 (12 hl\u00f6), EduCity\nEDU_3030, Ryhm\u00e4ty\u00f6 (10 hl\u00f6), EduCity\nICT_B2025, Ryhm\u00e4ty\u00f6 avo (16 hl\u00f6), ICT-City\nICT_B3024, Ryhm\u00e4ty\u00f6 avo (16 hl\u00f6), ICT-City\nICT_C2044, Ryhm\u00e4ty\u00f6 avo (16 hl\u00f6), ICT-City\nICT_C3040, Ryhm\u00e4ty\u00f6 avo (16 hl\u00f6), ICT-City\nLEM_B160a, Aatos (10 hl\u00f6), Lemppari\nLEM_B160b, Idea (10 hl\u00f6), Lemppari\nLEM_A307, Leirinuotio (8-12 hl\u00f6), Lemppari\nEDU_2057, Taidon portaat, EduCity\nEDU_2072, Ty\u00f6kahvila Aurinkokylpy /Esitystila avo, EduCity\nICT_C3044, Oppimistila muunto, ICT-City\nLEM_A104_aula, Lemmink\u00e4isen aula, Lemppari\nLEM_B143, Oppimistila muunto, Lemppari\nLEM_A308, Oppimistila byod, Lemppari\nLEM_B166, Kullervo, Lemppari\nEDU_3002, Henrik muunto byod, EduCity\nEDU_3004, Josef muunto byod, EduCity\nEDU_3003, Matias muunto byod, EduCity\nICT_C1032, Demotila, ICT-City\nEDU_3032, Ryhm\u00e4ty\u00f6 (16 hl\u00f6), EduCity\nEDU_3025, Ryhm\u00e4ty\u00f6 (16 hl\u00f6), EduCity"}, {"timeframe": "15:00 - 17:00", "start": "15:00", "end": "17:00", "title": "ICT Company info (Petteri Nakamura/DNV, ex Nixu)", "course_code": "", "location": "ICT_C1027_Lambda, LAMBDA, ICT-City"}], "2025-12-04": [{"timeframe": "8:00 - 10:00", "start": "8:00", "end": "10:00", "title": "Calculus", "course_code": "TE00CE14-3012", "location": "ICT_C1035_Delta, DELTA, ICT-City"}, {"timeframe": "10:00 - 12:00", "start": "10:00", "end": "12:00", "title": "Electrical Physics", "course_code": "TE00DH11-3002", "location": "ICT_C2036, Elektroniikkalaboratorio, ICT-City"}, {"timeframe": "12:00 - 14:00", "start": "12:00", "end": "14:00", "title": "Introduction to Programming", "course_code": "TE00CS88-3006", "location": "LEM_A177, IT-tila Saccharomyces - koneilla, Lemppari"}], "2025-12-05": [{"timeframe": "13:00 - 15:00", "start": "13:00", "end": "15:00", "title": "Calculus", "course_code": "TE00CE14-3012", "location": "ICT_C1042_Myy, MYY, ICT-City"}]}